percen/__init__.py
percen/percen.py
percen-1.0.0.dist-info/METADATA
percen-1.0.0.dist-info/WHEEL
percen-1.0.0.dist-info/top_level.txt
percen-1.0.0.dist-info/RECORD
