Metadata-Version: 2.1
Name: percen
Version: 1.0.0
Summary: 확률 알고리즘을 도와주는 라이브러리입니다.
Home-page: UNKNOWN
Author: conis
License: MIT
Platform: UNKNOWN
Requires-Python: >=3
